README.md
setup.py
TTW123.egg-info/PKG-INFO
TTW123.egg-info/SOURCES.txt
TTW123.egg-info/dependency_links.txt
TTW123.egg-info/requires.txt
TTW123.egg-info/top_level.txt
ttw/__init__.py
ttw/yy.py